tests/test_focal_statistics.py
tests/test_raster_windows.py
tests/focal_correlation_timeit.py
tests/test_rolling.py
tests/__init__.py
tests/test_focal_function.py
tests/test_strata_stats.py
tests/test_focal_correlations.py
focal_stats/utils.py
focal_stats/raster_window.py
focal_stats/focal_function.py
focal_stats/__init__.py
focal_stats/stat_helper_functions.py
focal_stats/types.py
focal_stats/window.py
focal_stats/rolling/__init__.py
focal_stats/rolling/rolling_window.py
focal_stats/rolling/rolling_stats.py
focal_stats/grouped_stats/grouped_stats.py
focal_stats/grouped_stats/_grouped_max.pyx
focal_stats/grouped_stats/utils.py
focal_stats/grouped_stats/_grouped_mean.pxd
focal_stats/grouped_stats/_grouped_linear_regression.pyx
focal_stats/grouped_stats/_grouped_correlation.pxd
focal_stats/grouped_stats/_grouped_max.cpython-39-x86_64-linux-gnu.so
focal_stats/grouped_stats/_grouped_mean.pyx
focal_stats/grouped_stats/_grouped_count.cpython-39-x86_64-linux-gnu.so
focal_stats/grouped_stats/_grouped_min.pyx
focal_stats/grouped_stats/__init__.py
focal_stats/grouped_stats/_grouped_count.pxd
focal_stats/grouped_stats/_grouped_linear_regression.pxd
focal_stats/grouped_stats/_grouped_correlation.cpython-39-x86_64-linux-gnu.so
focal_stats/grouped_stats/_grouped_min.pxd
focal_stats/grouped_stats/_grouped_count.pyx
focal_stats/grouped_stats/_grouped_std.pyx
focal_stats/grouped_stats/_grouped_std.cpython-39-x86_64-linux-gnu.so
focal_stats/grouped_stats/_grouped_min.cpython-39-x86_64-linux-gnu.so
focal_stats/grouped_stats/_grouped_std.pxd
focal_stats/grouped_stats/_grouped_linear_regression.cpython-39-x86_64-linux-gnu.so
focal_stats/grouped_stats/_grouped_mean.cpython-39-x86_64-linux-gnu.so
focal_stats/grouped_stats/_grouped_max.pxd
focal_stats/grouped_stats/_grouped_correlation.pyx
focal_stats/focal_stats/_focal_statistics_core.cpython-39-x86_64-linux-gnu.so
focal_stats/focal_stats/iteration_params.pxd
focal_stats-0.1.0.dist-info/top_level.txt
focal_stats-0.1.0.dist-info/RECORD
focal_stats-0.1.0.dist-info/LICENSE
focal_stats-0.1.0.dist-info/METADATA
focal_stats-0.1.0.dist-info/WHEEL
