Metadata-Version: 2.1
Name: focal_stats
Version: 0.1.0
Author-email: Jasper Roebroek <roebroek.jasper@gmail.com>
License: MIT License
Project-URL: repository, https://github.com/jasperroebroek/focal-stats
Project-URL: documentation, https://focal-stats.readthedocs.io/en/latest/index.html
Requires-Python: >=3.9
License-File: LICENSE
Requires-Dist: numpy
Requires-Dist: numpydantic
Requires-Dist: joblib
Requires-Dist: pandas
Provides-Extra: documentation
Requires-Dist: sphinx; extra == "documentation"
Requires-Dist: sphinx_rtd_theme; extra == "documentation"
Requires-Dist: numpydoc; extra == "documentation"
Requires-Dist: jupyter; extra == "documentation"
Requires-Dist: matplotlib; extra == "documentation"
Provides-Extra: develop
Requires-Dist: cython; extra == "develop"
Requires-Dist: sphinx; extra == "develop"
Requires-Dist: sphinx_rtd_theme; extra == "develop"
Requires-Dist: numpydoc; extra == "develop"
Requires-Dist: scipy; extra == "develop"
Requires-Dist: jupyter; extra == "develop"
Requires-Dist: matplotlib; extra == "develop"
Requires-Dist: pytest; extra == "develop"
Requires-Dist: joblib; extra == "develop"
Requires-Dist: statsmodels; extra == "develop"
Provides-Extra: test
Requires-Dist: scipy; extra == "test"
Requires-Dist: pytest; extra == "test"
Requires-Dist: statsmodels; extra == "test"
